sphinxnotes/data/__init__.py
sphinxnotes/data/data.py
sphinxnotes/data/meta.py
sphinxnotes/data/py.typed
sphinxnotes/data/examples/__init__.py
sphinxnotes/data/examples/datadomain.py
sphinxnotes/data/examples/strict.py
sphinxnotes/data/render/__init__.py
sphinxnotes/data/render/datanodes.py
sphinxnotes/data/render/extractx.py
sphinxnotes/data/render/markup.py
sphinxnotes/data/render/pipeline.py
sphinxnotes/data/render/render.py
sphinxnotes/data/render/template.py
sphinxnotes/data/utils/__init__.py
sphinxnotes/data/utils/ctxproxy.py
sphinxnotes/data/utils/freestyle.py
sphinxnotes_data-1.0a33.dist-info/licenses/LICENSE
sphinxnotes_data-1.0a33.dist-info/METADATA
sphinxnotes_data-1.0a33.dist-info/WHEEL
sphinxnotes_data-1.0a33.dist-info/top_level.txt
sphinxnotes_data-1.0a33.dist-info/RECORD
